colcon_cd/__init__.py
colcon_cd-0.1.0.data/data/share/colcon_cd/function/colcon_cd.sh
colcon_cd-0.1.0.dist-info/METADATA
colcon_cd-0.1.0.dist-info/RECORD
colcon_cd-0.1.0.dist-info/WHEEL
colcon_cd-0.1.0.dist-info/entry_points.txt
colcon_cd-0.1.0.dist-info/top_level.txt
colcon_cd-0.1.0.dist-info/zip-safe
